thonny_codemate-0.1.7.dist-info/licenses/LICENSE
thonnycontrib/thonny_codemate/__init__.py
thonnycontrib/thonny_codemate/api.py
thonnycontrib/thonny_codemate/context_manager.py
thonnycontrib/thonny_codemate/edit_mode_handler.py
thonnycontrib/thonny_codemate/external_providers.py
thonnycontrib/thonny_codemate/i18n.py
thonnycontrib/thonny_codemate/llm_client.py
thonnycontrib/thonny_codemate/message_virtualization.py
thonnycontrib/thonny_codemate/model_manager.py
thonnycontrib/thonny_codemate/performance_monitor.py
thonnycontrib/thonny_codemate/prompts.py
thonnycontrib/thonny_codemate/ui/__init__.py
thonnycontrib/thonny_codemate/ui/chat_view.py
thonnycontrib/thonny_codemate/ui/chat_view_html.py
thonnycontrib/thonny_codemate/ui/custom_prompt_dialog.py
thonnycontrib/thonny_codemate/ui/markdown_renderer.py
thonnycontrib/thonny_codemate/ui/model_download_dialog.py
thonnycontrib/thonny_codemate/ui/settings_dialog.py
thonnycontrib/thonny_codemate/utils/__init__.py
thonnycontrib/thonny_codemate/utils/constants.py
thonnycontrib/thonny_codemate/utils/error_messages.py
thonnycontrib/thonny_codemate/utils/unified_error_handler.py
thonny_codemate-0.1.7.dist-info/METADATA
thonny_codemate-0.1.7.dist-info/WHEEL
thonny_codemate-0.1.7.dist-info/top_level.txt
thonny_codemate-0.1.7.dist-info/RECORD
