Metadata-Version: 2.4
Name: thonny-codemate
Version: 0.1.7
Summary: A Thonny IDE plugin that provides AI-powered coding assistance using local and cloud LLMs
Author-email: tokoroten <shinta.nakayama@gmail.com>
License: MIT
Project-URL: Homepage, https://github.com/tokoroten/thonny-codemate
Project-URL: Repository, https://github.com/tokoroten/thonny-codemate
Project-URL: Issues, https://github.com/tokoroten/thonny-codemate/issues
Keywords: thonny,plugin,llm,ai,code-assistant,education
Classifier: Development Status :: 3 - Alpha
Classifier: Intended Audience :: Education
Classifier: Intended Audience :: Developers
Classifier: License :: OSI Approved :: MIT License
Classifier: Programming Language :: Python :: 3
Classifier: Programming Language :: Python :: 3.10
Classifier: Programming Language :: Python :: 3.11
Classifier: Programming Language :: Python :: 3.12
Classifier: Programming Language :: Python :: 3.13
Classifier: Topic :: Education
Classifier: Topic :: Software Development :: Code Generators
Requires-Python: >=3.10
License-File: LICENSE
Requires-Dist: thonny>=4.0.0
Requires-Dist: huggingface-hub[hf_xet]>=0.16.0
Requires-Dist: tkinterweb[javascript]>=3.24
Requires-Dist: pythonmonkey>=0.2.0
Requires-Dist: markdown>=3.5
Requires-Dist: pygments>=2.17
Requires-Dist: llama-cpp-python>=0.3.9
Requires-Dist: openai>=1.0.0
Provides-Extra: cuda
Provides-Extra: metal
Provides-Extra: external-only
Provides-Extra: dev
Requires-Dist: pytest>=7.0; extra == "dev"
Requires-Dist: pytest-cov>=4.0; extra == "dev"
Requires-Dist: pytest-mock>=3.10.0; extra == "dev"
Requires-Dist: debugpy>=1.6; extra == "dev"
Requires-Dist: black>=23.0; extra == "dev"
Requires-Dist: ruff>=0.1.0; extra == "dev"
Requires-Dist: llama-cpp-python>=0.3.9; extra == "dev"
Provides-Extra: test
Requires-Dist: pytest>=7.0; extra == "test"
Requires-Dist: pytest-cov>=4.0; extra == "test"
Requires-Dist: pytest-mock>=3.10.0; extra == "test"
Dynamic: license-file
